domainics/__init__.py
domainics/busitier.py
domainics/config.py
domainics/exception.py
domainics/json.py
domainics/pillar.py
domainics/util.py
domainics/__pycache__/__init__.cpython-35.pyc
domainics/__pycache__/busitier.cpython-35.pyc
domainics/__pycache__/exception.cpython-35.pyc
domainics/__pycache__/json.cpython-35.pyc
domainics/__pycache__/pillar.cpython-35.pyc
domainics/__pycache__/util.cpython-35.pyc
domainics/db/__init__.py
domainics/db/dmerge.py
domainics/db/drecall.py
domainics/db/dtable.py
domainics/db/pgsql.py
domainics/db/schema.py
domainics/db/sqlblock.py
domainics/db/__pycache__/__init__.cpython-35.pyc
domainics/db/__pycache__/dmerge.cpython-35.pyc
domainics/db/__pycache__/drecall.cpython-35.pyc
domainics/db/__pycache__/dtable.cpython-35.pyc
domainics/db/__pycache__/schema.cpython-35.pyc
domainics/db/__pycache__/sqlblock.cpython-35.pyc
domainics/domobj/__init__.py
domainics/domobj/dattr.py
domainics/domobj/dobject.py
domainics/domobj/dset.py
domainics/domobj/metaclass.py
domainics/domobj/pagination.py
domainics/domobj/reshape.py
domainics/domobj/typing.py
domainics/domobj/__pycache__/__init__.cpython-35.pyc
domainics/domobj/__pycache__/dattr.cpython-35.pyc
domainics/domobj/__pycache__/dobject.cpython-35.pyc
domainics/domobj/__pycache__/dset.cpython-35.pyc
domainics/domobj/__pycache__/metaclass.cpython-35.pyc
domainics/domobj/__pycache__/reshape.cpython-35.pyc
domainics/domobj/__pycache__/typing.cpython-35.pyc
domainics/server/__init__.py
domainics/server/server.py
domainics/server/single.py
domainics/server/win32.py
domainics/tornice/__init__.py
domainics/tornice/app.py
domainics/tornice/client.py
domainics/tornice/cookie.py
domainics/tornice/funchandler.py
domainics/tornice/route.py
domainics/tornice/route_path.py
domainics/tornice/static.py
domainics/tornice/__pycache__/__init__.cpython-35.pyc
domainics/tornice/__pycache__/app.cpython-35.pyc
domainics/tornice/__pycache__/cookie.cpython-35.pyc
domainics-0.3.5.dist-info/DESCRIPTION.rst
domainics-0.3.5.dist-info/METADATA
domainics-0.3.5.dist-info/RECORD
domainics-0.3.5.dist-info/WHEEL
domainics-0.3.5.dist-info/metadata.json
domainics-0.3.5.dist-info/top_level.txt
