Metadata-Version: 2.0
Name: domainics
Version: 0.3.5
Summary: Web Framwork with Domain-orieted architecure
Home-page: https://github.com/lcgong/domainics
Author: Chenggong Lyu
Author-email: lcgong@gmail.com
License: BSD
Platform: UNKNOWN
Classifier: Development Status :: 2 - Pre-Alpha
Classifier: Intended Audience :: Developers
Classifier: License :: OSI Approved :: BSD License
Classifier: Operating System :: Unix
Classifier: Operating System :: POSIX
Classifier: Operating System :: Microsoft :: Windows
Classifier: Programming Language :: Python
Classifier: Programming Language :: Python :: 3
Classifier: Programming Language :: Python :: 3.5
Classifier: Programming Language :: Python :: Implementation :: CPython
Classifier: Topic :: Utilities
Requires-Dist: arrow (>=0.6)
Requires-Dist: psycopg2 (>=2.6.1)
Requires-Dist: tornado (>=4.2)
